./.gitignore
./PKG-INFO
./README.md
./__init__.py
./pyproject.toml
./test.py
./vid_vec_rep.py
feluda_vid_vec_rep_clip-0.1.5.dist-info/METADATA
feluda_vid_vec_rep_clip-0.1.5.dist-info/WHEEL
feluda_vid_vec_rep_clip-0.1.5.dist-info/RECORD
